ourgroceries/__init__.py
ourgroceries/exceptions.py
ourgroceries-1.5.4.dist-info/LICENSE
ourgroceries-1.5.4.dist-info/METADATA
ourgroceries-1.5.4.dist-info/WHEEL
ourgroceries-1.5.4.dist-info/top_level.txt
ourgroceries-1.5.4.dist-info/RECORD
