Metadata-Version: 2.1
Name: ourgroceries
Version: 1.5.4
Summary: Our Groceries Unofficial Python Package
Home-page: https://github.com/ljmerza/py-our-groceries
Author: Leonardo Merza
Author-email: ljmerza@gmail.com
License: MIT
Keywords: unoffical our groceries api
Classifier: Programming Language :: Python :: 3
Classifier: License :: OSI Approved :: MIT License
Classifier: Operating System :: OS Independent
Requires-Python: >=3.5
License-File: LICENSE
Requires-Dist: aiohttp>=3.6.1
Requires-Dist: beautifulsoup4>=4.7.1
